{"metadata":{"modules":{"imports":[],"exports":{"exported":[],"specifiers":[]}},"usedHelpers":[]},"ignored":false,"code":"$('window').on('keypress', function (event) {\n  alert('stop being dumb');\n});","ast":null,"map":{"version":3,"sources":["/client/components/search/js/search.js"],"names":[],"mappings":"AAAA,CAAC,CAAC,QAAQ,CAAC,CAAC,EAAE,CAAC,UAAU,EAAE,UAAS,KAAK,EAAE;AACzC,OAAK,CAAC,iBAAiB,CAAC,CAAC;CAC1B,CAAC,CAAC","file":"/client/components/search/js/search.js.map","sourcesContent":["$('window').on('keypress', function(event) {\r\n  alert('stop being dumb');\r\n});"]},"hash":"1e46680939ba486091d6e47a439cb2b1f8d716f1"}
